{
    "custom_stats": {},
    "global_custom_stats": {},
    "plays": [
        {
            "play": {
                "duration": {
                    "start": "2025-10-29T16:13:00.800441Z"
                },
                "id": "a002a503-ae2b-1ed7-0603-000000000001",
                "name": "all",
                "path": "/home/elastisyschangeme/SBOM2/compliantkubernetes-kubespray/tmp/sbom/aws/dump-image-vars.yml:2"
            },
            "tasks": []
        }
    ],
    "stats": {}
}
